sampleplan/__init__.py
sampleplan/sampleplan.dll
sampleplan/sampleplan.py
sampleplan-0.1.1.dist-info/licenses/LICENSE
sampleplan-0.1.1.dist-info/METADATA
sampleplan-0.1.1.dist-info/WHEEL
sampleplan-0.1.1.dist-info/top_level.txt
sampleplan-0.1.1.dist-info/RECORD
