Metadata-Version: 2.4
Name: sampleplan
Version: 0.1.1
Summary: Fast balanced sequence sampling via a compiled Nim backend
Author-email: Maxime Larocque <maxime.larocque@randomschemes.com>
License-Expression: MIT
Project-URL: Homepage, https://github.com/HistoryBeginsAtSumer/sampleplan
Project-URL: Source, https://github.com/HistoryBeginsAtSumer/sampleplan
Project-URL: Tracker, https://github.com/HistoryBeginsAtSumer/sampleplan/issues
Keywords: sampling,random,balanced,permutation,simulation,nim,ctypes
Classifier: Development Status :: 3 - Alpha
Classifier: Intended Audience :: Developers
Classifier: Programming Language :: Python :: 3
Classifier: Programming Language :: Python :: 3.8
Classifier: Programming Language :: Python :: 3.9
Classifier: Programming Language :: Python :: 3.10
Classifier: Programming Language :: Python :: 3.11
Classifier: Programming Language :: Python :: 3.12
Classifier: Operating System :: Microsoft :: Windows
Classifier: Topic :: Scientific/Engineering
Classifier: Topic :: Software Development :: Libraries
Classifier: Topic :: Utilities
Requires-Python: >=3.8
License-File: LICENSE
Requires-Dist: numpy>=1.21
Dynamic: license-file
